<?xml version="1.0" encoding="utf-8"?>
<ndm xmlns:xsi="http://www.w3.org/2001/XMLSchema-instance" xsi:noNamespaceSchemaLocation="http://sanaregistry.org/r/ndmxml/ndmxml-1.0-master.xsd">
<cdm id="CCSDS_CDM_VERS" version="1.0">
<header>
<CREATION_DATE>2020-02-02T02:24:00.000000</CREATION_DATE>
<ORIGINATOR>CLOSEAP</ORIGINATOR>
<MESSAGE_ID>00000A_00999A_2002030224_2002020224</MESSAGE_ID>
</header>
<body>
<relativeMetadataData>
<COMMENT>0.465585567063930E-001    0.250    1.741    0.250    4.000    0.250    4.000</COMMENT>
<TCA>2020-02-03T02:24:00.006677</TCA>
<MISS_DISTANCE units="m">30.4571816021522</MISS_DISTANCE>
<RELATIVE_SPEED units="m/s">15202.9621034065</RELATIVE_SPEED>
<relativeStateVector>
<RELATIVE_POSITION_R units="m">29.3227976131686</RELATIVE_POSITION_R>
<RELATIVE_POSITION_T units="m">-0.367446982756458</RELATIVE_POSITION_T>
<RELATIVE_POSITION_N units="m">8.22669034085487</RELATIVE_POSITION_N>
<RELATIVE_VELOCITY_R units="m/s">-42.3380669888447</RELATIVE_VELOCITY_R>
<RELATIVE_VELOCITY_T units="m/s">-15193.7411982503</RELATIVE_VELOCITY_T>
<RELATIVE_VELOCITY_N units="m/s">-527.723986842662</RELATIVE_VELOCITY_N>
</relativeStateVector>
<START_SCREEN_PERIOD>2020-02-02T02:24:00.000000Z</START_SCREEN_PERIOD>
<STOP_SCREEN_PERIOD>2020-02-12T02:24:00.000000Z</STOP_SCREEN_PERIOD>
<SCREEN_VOLUME_FRAME>RTN</SCREEN_VOLUME_FRAME>
<SCREEN_VOLUME_SHAPE>ELLIPSOID</SCREEN_VOLUME_SHAPE>
<SCREEN_VOLUME_X units="m">9999000.00000000</SCREEN_VOLUME_X>
<SCREEN_VOLUME_Y units="m">9999000.00000000</SCREEN_VOLUME_Y>
<SCREEN_VOLUME_Z units="m">9999000.00000000</SCREEN_VOLUME_Z>
<SCREEN_ENTRY_TIME>2020-02-03T02:11:45.505330Z</SCREEN_ENTRY_TIME>
<SCREEN_EXIT_TIME>2020-02-03T02:36:15.415236Z</SCREEN_EXIT_TIME>
<COLLISION_PROBABILITY>0.352175891957769E-001</COLLISION_PROBABILITY>
<COLLISION_PROBABILITY_METHOD>AKELLAALFRIEND-2000</COLLISION_PROBABILITY_METHOD>
</relativeMetadataData>
<segment>
<metadata>
<COMMENT>BASED ON GMV/SSTODSW</COMMENT>
<COMMENT>HBR FROM CONF PANEL</COMMENT>
<OBJECT>OBJECT1</OBJECT>
<OBJECT_DESIGNATOR>00000A</OBJECT_DESIGNATOR>
<CATALOG_NAME>CLOSEAP</CATALOG_NAME>
<OBJECT_NAME>DUMMY_A</OBJECT_NAME>
<INTERNATIONAL_DESIGNATOR>2000-000A</INTERNATIONAL_DESIGNATOR>
<EPHEMERIS_NAME>GMV/SSTODSW</EPHEMERIS_NAME>
<COVARIANCE_METHOD>DEFAULT</COVARIANCE_METHOD>
<MANEUVERABLE>N/A</MANEUVERABLE>
<REF_FRAME>EME2000</REF_FRAME>
</metadata>
<data>
<odParameters>
</odParameters>
<additionalParameters>
<AREA_PC units="m**2">78.5398163397448</AREA_PC>
<CD_AREA_OVER_MASS units="m**2/kg">0.126105011081956E-001</CD_AREA_OVER_MASS>
<CR_AREA_OVER_MASS units="m**2/kg">0.764272794436094E-002</CR_AREA_OVER_MASS>
</additionalParameters>
<stateVector>
<X units="km">1074.32222646047</X>
<Y units="km">4949.56212412912</Y>
<Z units="km">-4702.70031418548</Z>
<X_DOT units="km/s">-5.45380714792049</X_DOT>
<Y_DOT units="km/s">4.20450787040925</Y_DOT>
<Z_DOT units="km/s">3.18856354885378</Z_DOT>
</stateVector>
<covarianceMatrix>
<CR_R units="m**2">141.162224670601</CR_R>
<CT_R units="m**2">604.828142298407</CT_R>
<CT_T units="m**2">8731.36618474692</CT_T>
<CN_R units="m**2">6.70606438903040</CN_R>
<CN_T units="m**2">36.2761808780738</CN_T>
<CN_N units="m**2">173.845231434505</CN_N>
<CRDOT_R units="m**2/s">-0.503325491764332</CRDOT_R>
<CRDOT_T units="m**2/s">-8.44687357179379</CRDOT_T>
<CRDOT_N units="m**2/s">-0.289634015779779E-001</CRDOT_N>
<CRDOT_RDOT units="m**2/s**2">0.837752710567503E-002</CRDOT_RDOT>
<CTDOT_R units="m**2/s">-0.155593747394919</CTDOT_R>
<CTDOT_T units="m**2/s">-0.682506852178737</CTDOT_T>
<CTDOT_N units="m**2/s">-0.739075853010805E-002</CTDOT_N>
<CTDOT_RDOT units="m**2/s**2">0.572036349460869E-003</CTDOT_RDOT>
<CTDOT_TDOT units="m**2/s**2">0.171550147877804E-003</CTDOT_TDOT>
<CNDOT_R units="m**2/s">-0.189691842413494E-002</CNDOT_R>
<CNDOT_T units="m**2/s">-0.431349804823708E-001</CNDOT_T>
<CNDOT_N units="m**2/s">0.853319217156176E-001</CNDOT_N>
<CNDOT_RDOT units="m**2/s**2">0.333436265011820E-004</CNDOT_RDOT>
<CNDOT_TDOT units="m**2/s**2">0.211035206368319E-005</CNDOT_TDOT>
<CNDOT_NDOT units="m**2/s**2">0.372165431874427E-003</CNDOT_NDOT>
</covarianceMatrix>
</data>
</segment>
<segment>
<metadata>
<COMMENT>BASED ON GMV/SSTODSW</COMMENT>
<COMMENT>HBR FROM CONF PANEL</COMMENT>
<OBJECT>OBJECT2</OBJECT>
<OBJECT_DESIGNATOR>00999A</OBJECT_DESIGNATOR>
<CATALOG_NAME>CLOSEAP</CATALOG_NAME>
<OBJECT_NAME>DUMMY_B</OBJECT_NAME>
<INTERNATIONAL_DESIGNATOR>2000-999A</INTERNATIONAL_DESIGNATOR>
<EPHEMERIS_NAME>GMV/SSTODSW</EPHEMERIS_NAME>
<COVARIANCE_METHOD>DEFAULT</COVARIANCE_METHOD>
<MANEUVERABLE>N/A</MANEUVERABLE>
<REF_FRAME>EME2000</REF_FRAME>
</metadata>
<data>
<odParameters>
</odParameters>
<additionalParameters>
<AREA_PC units="m**2">78.5398163397448</AREA_PC>
<CD_AREA_OVER_MASS units="m**2/kg">0.126105011081956E-001</CD_AREA_OVER_MASS>
<CR_AREA_OVER_MASS units="m**2/kg">0.764272794436094E-002</CR_AREA_OVER_MASS>
</additionalParameters>
<stateVector>
<X units="km">1074.33262525437</X>
<Y units="km">4949.58640519997</Y>
<Z units="km">-4702.71547777987</Z>
<X_DOT units="km/s">5.09923077324360</X_DOT>
<Y_DOT units="km/s">-4.47647291675036</Y_DOT>
<Z_DOT units="km/s">-3.47507058914129</Z_DOT>
</stateVector>
<covarianceMatrix>
<CR_R units="m**2">131.050467353269</CR_R>
<CT_R units="m**2">-642.680522841956</CT_R>
<CT_T units="m**2">4676.51308335847</CT_T>
<CN_R units="m**2">-2.96437192900254</CN_R>
<CN_T units="m**2">18.7338524283381</CN_T>
<CN_N units="m**2">101.675535439060</CN_N>
<CRDOT_R units="m**2/s">0.551194913470480</CRDOT_R>
<CRDOT_T units="m**2/s">-4.14217784820422</CRDOT_T>
<CRDOT_N units="m**2/s">-0.175329599038780E-001</CRDOT_N>
<CRDOT_RDOT units="m**2/s**2">0.375049030164118E-002</CRDOT_RDOT>
<CTDOT_R units="m**2/s">-0.139838915285228</CTDOT_R>
<CTDOT_T units="m**2/s">0.674341419293306</CTDOT_T>
<CTDOT_N units="m**2/s">0.311123970410375E-002</CTDOT_N>
<CTDOT_RDOT units="m**2/s**2">-0.576412335273337E-003</CTDOT_RDOT>
<CTDOT_TDOT units="m**2/s**2">0.149315289879604E-003</CTDOT_TDOT>
<CNDOT_R units="m**2/s">0.695914283088325E-002</CNDOT_R>
<CNDOT_T units="m**2/s">-0.191073118795742E-001</CNDOT_T>
<CNDOT_N units="m**2/s">-0.362721485397015E-001</CNDOT_N>
<CNDOT_RDOT units="m**2/s**2">0.200269093194060E-004</CNDOT_RDOT>
<CNDOT_TDOT units="m**2/s**2">-0.744002344775705E-005</CNDOT_TDOT>
<CNDOT_NDOT units="m**2/s**2">0.116745722106912E-003</CNDOT_NDOT>
</covarianceMatrix>
</data>
</segment>
</body>
</cdm>
</ndm>
